{
    "version": "0.4",
    "title": "Services",
    "type": "section",
    "metadata": {
        "template_type": "section",
        "elementor_pro_required": false,
        "wp_page_template": "default"
    },
    "content": [
        {
            "id": "1cf16f29",
            "settings": {
                "padding": {
                    "unit": "px",
                    "top": "70",
                    "right": "0",
                    "bottom": "70",
                    "left": "0",
                    "isLinked": false
                },
                "background_background": "classic",
                "background_color": "#ffffff"
            },
            "elements": [
                {
                    "id": "68138437",
                    "settings": {
                        "_column_size": 100,
                        "margin": {
                            "unit": "px",
                            "top": "0",
                            "right": "0",
                            "bottom": "0",
                            "left": "0",
                            "isLinked": false
                        },
                        "padding": {
                            "unit": "px",
                            "top": "0",
                            "right": "0",
                            "bottom": "0",
                            "left": "0",
                            "isLinked": false
                        }
                    },
                    "elements": [
                        {
                            "id": "5d9a0d8c",
                            "settings": {
                                "margin": {
                                    "unit": "px",
                                    "top": "0",
                                    "right": 0,
                                    "bottom": "0",
                                    "left": 0,
                                    "isLinked": false
                                }
                            },
                            "elements": [
                                {
                                    "id": "180023b2",
                                    "settings": {
                                        "_column_size": 100
                                    },
                                    "elements": [
                                        {
                                            "id": "444a2ab",
                                            "settings": {
                                                "title": "Services",
                                                "header_size": "h3",
                                                "title_color": "rgba(16,45,94,0.6)",
                                                "typography_typography": "custom",
                                                "typography_font_family": "Playfair Display",
                                                "typography_font_size": {
                                                    "unit": "px",
                                                    "size": 24
                                                },
                                                "typography_font_size_mobile": {
                                                    "unit": "px",
                                                    "size": 22
                                                },
                                                "_animation": "fadeIn",
                                                "animation_duration": "slow",
                                                "align": "center"
                                            },
                                            "elements": [],
                                            "isInner": false,
                                            "widgetType": "heading",
                                            "elType": "widget"
                                        },
                                        {
                                            "id": "1b087d00",
                                            "settings": {
                                                "title": "Heading",
                                                "header_size": "h1",
                                                "title_color": "#102d5e",
                                                "typography_typography": "custom",
                                                "typography_font_family": "Playfair Display",
                                                "typography_font_size": {
                                                    "unit": "px",
                                                    "size": 50
                                                },
                                                "typography_font_size_mobile": {
                                                    "unit": "px",
                                                    "size": 36
                                                },
                                                "typography_line_height": {
                                                    "unit": "px",
                                                    "size": 60
                                                },
                                                "typography_line_height_mobile": {
                                                    "unit": "px",
                                                    "size": 44
                                                },
                                                "_margin_mobile": {
                                                    "unit": "px",
                                                    "top": "-10",
                                                    "right": "0",
                                                    "bottom": "0",
                                                    "left": "0",
                                                    "isLinked": false
                                                },
                                                "_animation": "fadeIn",
                                                "animation_duration": "slow",
                                                "align": "center",
                                                "_margin": {
                                                    "unit": "px",
                                                    "top": "-10",
                                                    "right": "0",
                                                    "bottom": "0",
                                                    "left": "0",
                                                    "isLinked": false
                                                }
                                            },
                                            "elements": [],
                                            "isInner": false,
                                            "widgetType": "heading",
                                            "elType": "widget"
                                        }
                                    ],
                                    "isInner": true,
                                    "elType": "column"
                                }
                            ],
                            "isInner": true,
                            "elType": "section"
                        },
                        {
                            "id": "58616558",
                            "settings": {
                                "structure": "30"
                            },
                            "elements": [
                                {
                                    "id": "6c557f3e",
                                    "settings": {
                                        "_column_size": 33,
                                        "_inline_size": null,
                                        "_inline_size_tablet": 50,
                                        "border_border": "solid",
                                        "border_width": {
                                            "unit": "px",
                                            "top": "1",
                                            "right": "1",
                                            "bottom": "1",
                                            "left": "1",
                                            "isLinked": true
                                        },
                                        "border_color": "#eeeeee",
                                        "border_radius": {
                                            "unit": "px",
                                            "top": "3",
                                            "right": "3",
                                            "bottom": "3",
                                            "left": "3",
                                            "isLinked": true
                                        },
                                        "box_shadow_hover_box_shadow_type": "yes",
                                        "box_shadow_hover_box_shadow": {
                                            "horizontal": 0,
                                            "vertical": 0,
                                            "blur": 80,
                                            "spread": 20,
                                            "color": "rgba(16,45,94,0.17)"
                                        },
                                        "margin": {
                                            "unit": "px",
                                            "top": "0",
                                            "right": "15",
                                            "bottom": "0",
                                            "left": "15",
                                            "isLinked": false
                                        },
                                        "padding": {
                                            "unit": "px",
                                            "top": "40",
                                            "right": "40",
                                            "bottom": "40",
                                            "left": "40",
                                            "isLinked": true
                                        }
                                    },
                                    "elements": [
                                        {
                                            "id": "484f3566",
                                            "settings": {
                                                "image": {
                                                    "url": "https:\/\/wp.envatoextensions.com\/kit-68\/wp-content\/uploads\/sites\/71\/2018\/09\/robin-spielmann-591331-unsplash.jpg",
                                                    "id": 147
                                                },
                                                "image_size": "thumbnail",
                                                "image_border_radius": {
                                                    "unit": "%",
                                                    "top": "50",
                                                    "right": "50",
                                                    "bottom": "50",
                                                    "left": "50",
                                                    "isLinked": true
                                                }
                                            },
                                            "elements": [],
                                            "isInner": false,
                                            "widgetType": "image",
                                            "elType": "widget"
                                        },
                                        {
                                            "id": "5833d201",
                                            "settings": {
                                                "title": "Service",
                                                "align": "center",
                                                "title_color": "#102d5e"
                                            },
                                            "elements": [],
                                            "isInner": false,
                                            "widgetType": "heading",
                                            "elType": "widget"
                                        },
                                        {
                                            "id": "3807fb62",
                                            "settings": {
                                                "editor": "<p>Aliquet adipiscing vivamus ultrices ipsum, commodo vitae, elit nec.<\/p>",
                                                "align": "center",
                                                "text_color": "#7c7c7c",
                                                "typography_typography": "custom",
                                                "typography_font_family": "Open Sans",
                                                "typography_font_size": {
                                                    "unit": "px",
                                                    "size": 16
                                                },
                                                "typography_font_weight": "400",
                                                "typography_line_height": {
                                                    "unit": "px",
                                                    "size": 26
                                                }
                                            },
                                            "elements": [],
                                            "isInner": false,
                                            "widgetType": "text-editor",
                                            "elType": "widget"
                                        },
                                        {
                                            "id": "73e77084",
                                            "settings": {
                                                "icon_list": [
                                                    {
                                                        "text": "List Item",
                                                        "icon": "fa fa-check",
                                                        "_id": "504ca81",
                                                        "link": {
                                                            "url": "",
                                                            "is_external": "",
                                                            "nofollow": ""
                                                        }
                                                    },
                                                    {
                                                        "text": "List Item",
                                                        "icon": "fa fa-check",
                                                        "_id": "116fbe7",
                                                        "link": {
                                                            "url": "",
                                                            "is_external": "",
                                                            "nofollow": ""
                                                        }
                                                    },
                                                    {
                                                        "text": "List Item",
                                                        "icon": "fa fa-check",
                                                        "_id": "372d18c",
                                                        "link": {
                                                            "url": "",
                                                            "is_external": "",
                                                            "nofollow": ""
                                                        }
                                                    }
                                                ],
                                                "space_between": {
                                                    "unit": "px",
                                                    "size": 6
                                                },
                                                "icon_align": "center",
                                                "icon_color": "#102d5e",
                                                "text_color": "#7c7c7c",
                                                "text_indent": {
                                                    "unit": "px",
                                                    "size": 9
                                                },
                                                "icon_typography_typography": "custom",
                                                "icon_typography_font_size": {
                                                    "unit": "px",
                                                    "size": 14
                                                },
                                                "icon_typography_font_weight": "600"
                                            },
                                            "elements": [],
                                            "isInner": false,
                                            "widgetType": "icon-list",
                                            "elType": "widget"
                                        },
                                        {
                                            "id": "5f00292e",
                                            "settings": {
                                                "text": "Learn More",
                                                "typography_typography": "custom",
                                                "typography_font_size": {
                                                    "unit": "px",
                                                    "size": 14
                                                },
                                                "typography_font_weight": "600",
                                                "typography_text_transform": "uppercase",
                                                "background_color": "#102d5e",
                                                "border_radius": {
                                                    "unit": "px",
                                                    "top": "3",
                                                    "right": "3",
                                                    "bottom": "3",
                                                    "left": "3",
                                                    "isLinked": true
                                                },
                                                "text_padding": {
                                                    "unit": "px",
                                                    "top": "14",
                                                    "right": "34",
                                                    "bottom": "14",
                                                    "left": "34",
                                                    "isLinked": false
                                                },
                                                "_margin": {
                                                    "unit": "px",
                                                    "top": "20",
                                                    "right": "0",
                                                    "bottom": "0",
                                                    "left": "0",
                                                    "isLinked": false
                                                },
                                                "button_background_hover_color": "#7c7c7c",
                                                "_animation": "fadeIn",
                                                "animation_duration": "fast",
                                                "align": "center"
                                            },
                                            "elements": [],
                                            "isInner": false,
                                            "widgetType": "button",
                                            "elType": "widget"
                                        }
                                    ],
                                    "isInner": true,
                                    "elType": "column"
                                },
                                {
                                    "id": "10edbfe7",
                                    "settings": {
                                        "_column_size": 33,
                                        "_inline_size": null,
                                        "_inline_size_tablet": 50,
                                        "border_border": "solid",
                                        "border_width": {
                                            "unit": "px",
                                            "top": "1",
                                            "right": "1",
                                            "bottom": "1",
                                            "left": "1",
                                            "isLinked": true
                                        },
                                        "border_color": "#eeeeee",
                                        "border_radius": {
                                            "unit": "px",
                                            "top": "3",
                                            "right": "3",
                                            "bottom": "3",
                                            "left": "3",
                                            "isLinked": true
                                        },
                                        "box_shadow_hover_box_shadow_type": "yes",
                                        "box_shadow_hover_box_shadow": {
                                            "horizontal": 0,
                                            "vertical": 0,
                                            "blur": 80,
                                            "spread": 20,
                                            "color": "rgba(16,45,94,0.17)"
                                        },
                                        "margin": {
                                            "unit": "px",
                                            "top": "0",
                                            "right": "15",
                                            "bottom": "0",
                                            "left": "15",
                                            "isLinked": false
                                        },
                                        "margin_mobile": {
                                            "unit": "px",
                                            "top": "30",
                                            "right": "15",
                                            "bottom": "0",
                                            "left": "15",
                                            "isLinked": false
                                        },
                                        "padding": {
                                            "unit": "px",
                                            "top": "40",
                                            "right": "40",
                                            "bottom": "40",
                                            "left": "40",
                                            "isLinked": true
                                        }
                                    },
                                    "elements": [
                                        {
                                            "id": "218f34f9",
                                            "settings": {
                                                "image": {
                                                    "url": "https:\/\/wp.envatoextensions.com\/kit-68\/wp-content\/uploads\/sites\/71\/2018\/09\/robin-spielmann-5913311-unsplash.jpg",
                                                    "id": 148
                                                },
                                                "image_size": "thumbnail",
                                                "image_border_radius": {
                                                    "unit": "%",
                                                    "top": "50",
                                                    "right": "50",
                                                    "bottom": "50",
                                                    "left": "50",
                                                    "isLinked": true
                                                }
                                            },
                                            "elements": [],
                                            "isInner": false,
                                            "widgetType": "image",
                                            "elType": "widget"
                                        },
                                        {
                                            "id": "504a4ccb",
                                            "settings": {
                                                "title": "Service",
                                                "align": "center",
                                                "title_color": "#102d5e"
                                            },
                                            "elements": [],
                                            "isInner": false,
                                            "widgetType": "heading",
                                            "elType": "widget"
                                        },
                                        {
                                            "id": "1d94fe33",
                                            "settings": {
                                                "editor": "<p>Aliquet adipiscing vivamus ultrices ipsum, commodo vitae, elit nec.<\/p>",
                                                "align": "center",
                                                "text_color": "#7c7c7c",
                                                "typography_typography": "custom",
                                                "typography_font_family": "Open Sans",
                                                "typography_font_size": {
                                                    "unit": "px",
                                                    "size": 16
                                                },
                                                "typography_font_weight": "400",
                                                "typography_line_height": {
                                                    "unit": "px",
                                                    "size": 26
                                                }
                                            },
                                            "elements": [],
                                            "isInner": false,
                                            "widgetType": "text-editor",
                                            "elType": "widget"
                                        },
                                        {
                                            "id": "3d8344f",
                                            "settings": {
                                                "icon_list": [
                                                    {
                                                        "text": "List Item",
                                                        "icon": "fa fa-check",
                                                        "_id": "504ca81",
                                                        "link": {
                                                            "url": "",
                                                            "is_external": "",
                                                            "nofollow": ""
                                                        }
                                                    },
                                                    {
                                                        "text": "List Item",
                                                        "icon": "fa fa-check",
                                                        "_id": "116fbe7",
                                                        "link": {
                                                            "url": "",
                                                            "is_external": "",
                                                            "nofollow": ""
                                                        }
                                                    },
                                                    {
                                                        "text": "List Item",
                                                        "icon": "fa fa-check",
                                                        "_id": "372d18c",
                                                        "link": {
                                                            "url": "",
                                                            "is_external": "",
                                                            "nofollow": ""
                                                        }
                                                    }
                                                ],
                                                "space_between": {
                                                    "unit": "px",
                                                    "size": 6
                                                },
                                                "icon_align": "center",
                                                "icon_color": "#102d5e",
                                                "text_color": "#7c7c7c",
                                                "text_indent": {
                                                    "unit": "px",
                                                    "size": 9
                                                },
                                                "icon_typography_typography": "custom",
                                                "icon_typography_font_size": {
                                                    "unit": "px",
                                                    "size": 14
                                                },
                                                "icon_typography_font_weight": "600"
                                            },
                                            "elements": [],
                                            "isInner": false,
                                            "widgetType": "icon-list",
                                            "elType": "widget"
                                        },
                                        {
                                            "id": "795cc00f",
                                            "settings": {
                                                "text": "Learn More",
                                                "typography_typography": "custom",
                                                "typography_font_size": {
                                                    "unit": "px",
                                                    "size": 14
                                                },
                                                "typography_font_weight": "600",
                                                "typography_text_transform": "uppercase",
                                                "background_color": "#102d5e",
                                                "border_radius": {
                                                    "unit": "px",
                                                    "top": "3",
                                                    "right": "3",
                                                    "bottom": "3",
                                                    "left": "3",
                                                    "isLinked": true
                                                },
                                                "text_padding": {
                                                    "unit": "px",
                                                    "top": "14",
                                                    "right": "34",
                                                    "bottom": "14",
                                                    "left": "34",
                                                    "isLinked": false
                                                },
                                                "_margin": {
                                                    "unit": "px",
                                                    "top": "20",
                                                    "right": "0",
                                                    "bottom": "0",
                                                    "left": "0",
                                                    "isLinked": false
                                                },
                                                "button_background_hover_color": "#7c7c7c",
                                                "_animation": "fadeIn",
                                                "animation_duration": "fast",
                                                "align": "center"
                                            },
                                            "elements": [],
                                            "isInner": false,
                                            "widgetType": "button",
                                            "elType": "widget"
                                        }
                                    ],
                                    "isInner": true,
                                    "elType": "column"
                                },
                                {
                                    "id": "1274428a",
                                    "settings": {
                                        "_column_size": 33,
                                        "_inline_size": null,
                                        "_inline_size_tablet": 100,
                                        "border_border": "solid",
                                        "border_width": {
                                            "unit": "px",
                                            "top": "1",
                                            "right": "1",
                                            "bottom": "1",
                                            "left": "1",
                                            "isLinked": true
                                        },
                                        "border_color": "#eeeeee",
                                        "border_radius": {
                                            "unit": "px",
                                            "top": "3",
                                            "right": "3",
                                            "bottom": "3",
                                            "left": "3",
                                            "isLinked": true
                                        },
                                        "box_shadow_hover_box_shadow_type": "yes",
                                        "box_shadow_hover_box_shadow": {
                                            "horizontal": 0,
                                            "vertical": 0,
                                            "blur": 80,
                                            "spread": 20,
                                            "color": "rgba(16,45,94,0.17)"
                                        },
                                        "margin": {
                                            "unit": "px",
                                            "top": "0",
                                            "right": "15",
                                            "bottom": "0",
                                            "left": "15",
                                            "isLinked": false
                                        },
                                        "margin_tablet": {
                                            "unit": "px",
                                            "top": "30",
                                            "right": "15",
                                            "bottom": "0",
                                            "left": "15",
                                            "isLinked": false
                                        },
                                        "padding": {
                                            "unit": "px",
                                            "top": "40",
                                            "right": "40",
                                            "bottom": "40",
                                            "left": "40",
                                            "isLinked": true
                                        }
                                    },
                                    "elements": [
                                        {
                                            "id": "7f723c47",
                                            "settings": {
                                                "image": {
                                                    "url": "https:\/\/wp.envatoextensions.com\/kit-68\/wp-content\/uploads\/sites\/71\/2018\/09\/robin-spielmann-5913312-unsplash.jpg",
                                                    "id": 145
                                                },
                                                "image_size": "thumbnail",
                                                "image_border_radius": {
                                                    "unit": "%",
                                                    "top": "50",
                                                    "right": "50",
                                                    "bottom": "50",
                                                    "left": "50",
                                                    "isLinked": true
                                                }
                                            },
                                            "elements": [],
                                            "isInner": false,
                                            "widgetType": "image",
                                            "elType": "widget"
                                        },
                                        {
                                            "id": "434ea0c2",
                                            "settings": {
                                                "title": "Service",
                                                "align": "center",
                                                "title_color": "#102d5e"
                                            },
                                            "elements": [],
                                            "isInner": false,
                                            "widgetType": "heading",
                                            "elType": "widget"
                                        },
                                        {
                                            "id": "4846e14b",
                                            "settings": {
                                                "editor": "<p>Aliquet adipiscing vivamus ultrices ipsum, commodo vitae, elit nec.<\/p>",
                                                "align": "center",
                                                "text_color": "#7c7c7c",
                                                "typography_typography": "custom",
                                                "typography_font_family": "Open Sans",
                                                "typography_font_size": {
                                                    "unit": "px",
                                                    "size": 16
                                                },
                                                "typography_font_weight": "400",
                                                "typography_line_height": {
                                                    "unit": "px",
                                                    "size": 26
                                                }
                                            },
                                            "elements": [],
                                            "isInner": false,
                                            "widgetType": "text-editor",
                                            "elType": "widget"
                                        },
                                        {
                                            "id": "3d83d933",
                                            "settings": {
                                                "icon_list": [
                                                    {
                                                        "text": "List Item",
                                                        "icon": "fa fa-check",
                                                        "_id": "504ca81",
                                                        "link": {
                                                            "url": "",
                                                            "is_external": "",
                                                            "nofollow": ""
                                                        }
                                                    },
                                                    {
                                                        "text": "List Item",
                                                        "icon": "fa fa-check",
                                                        "_id": "116fbe7",
                                                        "link": {
                                                            "url": "",
                                                            "is_external": "",
                                                            "nofollow": ""
                                                        }
                                                    },
                                                    {
                                                        "text": "List Item",
                                                        "icon": "fa fa-check",
                                                        "_id": "372d18c",
                                                        "link": {
                                                            "url": "",
                                                            "is_external": "",
                                                            "nofollow": ""
                                                        }
                                                    }
                                                ],
                                                "space_between": {
                                                    "unit": "px",
                                                    "size": 6
                                                },
                                                "icon_align": "center",
                                                "icon_color": "#102d5e",
                                                "text_color": "#7c7c7c",
                                                "text_indent": {
                                                    "unit": "px",
                                                    "size": 9
                                                },
                                                "icon_typography_typography": "custom",
                                                "icon_typography_font_size": {
                                                    "unit": "px",
                                                    "size": 14
                                                },
                                                "icon_typography_font_weight": "600"
                                            },
                                            "elements": [],
                                            "isInner": false,
                                            "widgetType": "icon-list",
                                            "elType": "widget"
                                        },
                                        {
                                            "id": "5d81a5d1",
                                            "settings": {
                                                "text": "Learn More",
                                                "typography_typography": "custom",
                                                "typography_font_size": {
                                                    "unit": "px",
                                                    "size": 14
                                                },
                                                "typography_font_weight": "600",
                                                "typography_text_transform": "uppercase",
                                                "background_color": "#102d5e",
                                                "border_radius": {
                                                    "unit": "px",
                                                    "top": "3",
                                                    "right": "3",
                                                    "bottom": "3",
                                                    "left": "3",
                                                    "isLinked": true
                                                },
                                                "text_padding": {
                                                    "unit": "px",
                                                    "top": "14",
                                                    "right": "34",
                                                    "bottom": "14",
                                                    "left": "34",
                                                    "isLinked": false
                                                },
                                                "_margin": {
                                                    "unit": "px",
                                                    "top": "20",
                                                    "right": "0",
                                                    "bottom": "0",
                                                    "left": "0",
                                                    "isLinked": false
                                                },
                                                "button_background_hover_color": "#7c7c7c",
                                                "_animation": "fadeIn",
                                                "animation_duration": "fast",
                                                "align": "center"
                                            },
                                            "elements": [],
                                            "isInner": false,
                                            "widgetType": "button",
                                            "elType": "widget"
                                        }
                                    ],
                                    "isInner": true,
                                    "elType": "column"
                                }
                            ],
                            "isInner": true,
                            "elType": "section"
                        }
                    ],
                    "isInner": false,
                    "elType": "column"
                }
            ],
            "isInner": false,
            "elType": "section"
        }
    ]
}